Orange3_Chemometry-0.0.6-py3.7-nspkg.pth
Orange3_Chemometry-0.0.6.data/data/help/orange3-chemometry/.buildinfo
Orange3_Chemometry-0.0.6.data/data/help/orange3-chemometry/genindex.html
Orange3_Chemometry-0.0.6.data/data/help/orange3-chemometry/index.html
Orange3_Chemometry-0.0.6.data/data/help/orange3-chemometry/objects.inv
Orange3_Chemometry-0.0.6.data/data/help/orange3-chemometry/search.html
Orange3_Chemometry-0.0.6.data/data/help/orange3-chemometry/searchindex.js
Orange3_Chemometry-0.0.6.data/data/help/orange3-chemometry/_images/PLS.png
Orange3_Chemometry-0.0.6.data/data/help/orange3-chemometry/_sources/index.rst.txt
Orange3_Chemometry-0.0.6.data/data/help/orange3-chemometry/_sources/widgets/PLS.md.txt
Orange3_Chemometry-0.0.6.data/data/help/orange3-chemometry/_static/ajax-loader.gif
Orange3_Chemometry-0.0.6.data/data/help/orange3-chemometry/_static/basic.css
Orange3_Chemometry-0.0.6.data/data/help/orange3-chemometry/_static/comment-bright.png
Orange3_Chemometry-0.0.6.data/data/help/orange3-chemometry/_static/comment-close.png
Orange3_Chemometry-0.0.6.data/data/help/orange3-chemometry/_static/comment.png
Orange3_Chemometry-0.0.6.data/data/help/orange3-chemometry/_static/doctools.js
Orange3_Chemometry-0.0.6.data/data/help/orange3-chemometry/_static/documentation_options.js
Orange3_Chemometry-0.0.6.data/data/help/orange3-chemometry/_static/down-pressed.png
Orange3_Chemometry-0.0.6.data/data/help/orange3-chemometry/_static/down.png
Orange3_Chemometry-0.0.6.data/data/help/orange3-chemometry/_static/file.png
Orange3_Chemometry-0.0.6.data/data/help/orange3-chemometry/_static/jquery-3.2.1.js
Orange3_Chemometry-0.0.6.data/data/help/orange3-chemometry/_static/jquery.js
Orange3_Chemometry-0.0.6.data/data/help/orange3-chemometry/_static/language_data.js
Orange3_Chemometry-0.0.6.data/data/help/orange3-chemometry/_static/minus.png
Orange3_Chemometry-0.0.6.data/data/help/orange3-chemometry/_static/nature.css
Orange3_Chemometry-0.0.6.dist-info/LICENSE
Orange3_Chemometry-0.0.6.dist-info/METADATA
Orange3_Chemometry-0.0.6.dist-info/WHEEL
Orange3_Chemometry-0.0.6.dist-info/entry_points.txt
Orange3_Chemometry-0.0.6.dist-info/namespace_packages.txt
Orange3_Chemometry-0.0.6.dist-info/top_level.txt
Orange3_Chemometry-0.0.6.dist-info/RECORD
