Metadata-Version: 2.1
Name: Orange3-Chemometry
Version: 0.0.6
Summary: Add-on containing chemometry widgets
Home-page: UNKNOWN
Author: Georg Ramer
Author-email: georg@ramer.at
License: GPLv3
Keywords: orange3 add-on
Platform: UNKNOWN
Requires-Dist: Orange3
Requires-Dist: scikit-learn
Requires-Dist: numpy
